cqsat/__init__.py
cqsat/config.py
cqsat/log.py
cqsat/media_utils.py
cqsat/path.py
cqsat/utils.py
cqsat/cqsat_resource/bank/A.json
cqsat/cqsat_resource/bank/B.json
cqsat/cqsat_resource/bank/C.json
cqsat/cqsat_resource/bank/imgs/LK0497.jpg
cqsat/cqsat_resource/bank/imgs/LK0498.jpg
cqsat/cqsat_resource/bank/imgs/LK0499.jpg
cqsat/cqsat_resource/bank/imgs/LK0500.jpg
cqsat/cqsat_resource/bank/imgs/LK0501.jpg
cqsat/cqsat_resource/bank/imgs/LK0502.jpg
cqsat/cqsat_resource/bank/imgs/LK0503.jpg
cqsat/cqsat_resource/bank/imgs/LK0504.jpg
cqsat/cqsat_resource/bank/imgs/LK0505.jpg
cqsat/cqsat_resource/bank/imgs/LK0506.jpg
cqsat/cqsat_resource/bank/imgs/LK0507.jpg
cqsat/cqsat_resource/bank/imgs/LK0508.jpg
cqsat/cqsat_resource/bank/imgs/LK0509.jpg
cqsat/cqsat_resource/bank/imgs/LK0510.jpg
cqsat/cqsat_resource/bank/imgs/LK0511.jpg
cqsat/cqsat_resource/bank/imgs/LK0594.jpg
cqsat/cqsat_resource/bank/imgs/LK0595.jpg
cqsat/cqsat_resource/bank/imgs/LK0596.jpg
cqsat/cqsat_resource/bank/imgs/LK0597.jpg
cqsat/cqsat_resource/bank/imgs/LK0598.jpg
cqsat/cqsat_resource/bank/imgs/LK0599.jpg
cqsat/cqsat_resource/bank/imgs/LK0600.jpg
cqsat/cqsat_resource/bank/imgs/LK0601.jpg
cqsat/cqsat_resource/bank/imgs/LK0602.jpg
cqsat/cqsat_resource/bank/imgs/LK0603.jpg
cqsat/cqsat_resource/bank/imgs/LK0604.jpg
cqsat/cqsat_resource/bank/imgs/LK0605.jpg
cqsat/cqsat_resource/bank/imgs/LK0606.jpg
cqsat/cqsat_resource/bank/imgs/LK0607.jpg
cqsat/cqsat_resource/bank/imgs/LK0608.jpg
cqsat/cqsat_resource/bank/imgs/LK0609.jpg
cqsat/cqsat_resource/bank/imgs/LK0610.jpg
cqsat/cqsat_resource/bank/imgs/LK0611.jpg
cqsat/cqsat_resource/bank/imgs/LK0612.jpg
cqsat/cqsat_resource/bank/imgs/LK0613.jpg
cqsat/cqsat_resource/bank/imgs/LK0614.jpg
cqsat/cqsat_resource/bank/imgs/LK0734.jpg
cqsat/cqsat_resource/bank/imgs/LK0735.jpg
cqsat/cqsat_resource/bank/imgs/LK0736.jpg
cqsat/cqsat_resource/bank/imgs/LK0740.jpg
cqsat/cqsat_resource/bank/imgs/LK0741.jpg
cqsat/cqsat_resource/bank/imgs/LK0742.jpg
nonebot_plugin_cqsat-0.1.12.4.dist-info/LICENSE
nonebot_plugin_cqsat-0.1.12.4.dist-info/METADATA
nonebot_plugin_cqsat-0.1.12.4.dist-info/WHEEL
nonebot_plugin_cqsat-0.1.12.4.dist-info/top_level.txt
nonebot_plugin_cqsat-0.1.12.4.dist-info/RECORD
