Metadata-Version: 2.1
Name: nonebot-plugin-cqsat
Version: 0.1.12.4
Summary: nonebot2 业余无线电卫星
Home-page: https://github.com/yzyyz1387/cqsat
Author: yzyyz1387
Author-email: youzyyz1384@gmail.com
Keywords: ham,nonebot2,nonebot,radio,nonebot_plugin
Platform: any
Classifier: Programming Language :: Python :: 3
Classifier: License :: OSI Approved :: GNU Affero General Public License v3 or later (AGPLv3+)
Classifier: Operating System :: OS Independent
License-File: LICENSE
Requires-Dist: httpx
Requires-Dist: pyephem
Requires-Dist: python-dateutil
Requires-Dist: PyYAML
Requires-Dist: nonebot-adapter-onebot >=2.0.0-beta.1
Requires-Dist: nonebot2 >=2.0.0-beta.4
Requires-Dist: nonebot-plugin-apscheduler
